{
  "Tankulan": {
    "labels": ["January", "February", "March", "April", "May", "June"],
    "values": [120, 150, 180, 200, 170, 190]
  },
  "Sankanan": {
    "labels": ["January", "February", "March", "April", "May", "June"],
    "values": [100, 130, 160, 180, 150, 170]
  },
  "Dicklum": {
    "labels": ["January", "February", "March", "April", "May", "June"],
    "values": [80, 110, 140, 160, 130, 150]
  },
  "Lingion": {
    "labels": ["January", "February", "March", "April", "May", "June"],
    "values": [90, 120, 150, 170, 140, 160]
  }
}